<?xml version="1.0" encoding="windows-1251" ?>
<string_table>
	<string id="kb_active_jobs">
		<text>PDA</text>
	</string>
	<string id="kb_alife_command">
		<text>Order to attack</text>
	</string>
	<string id="kb_always_run">
		<text>Walk/Low crouch</text>
	</string>
	<string id="kb_artefact">
		<text>Artefact</text>
	</string>
	<string id="kb_backward">
		<text>Backward</text>
	</string>
	<string id="kb_binoculars">
		<text>Binoculars</text>
	</string>
	<string id="kb_buy_menu">
		<text>Buy menu</text>
	</string>
	<string id="kb_chat">
		<text>Chat</text>
	</string>
	<string id="kb_chat_team">
		<text>Team chat</text>
	</string>
	<string id="kb_console">
		<text>Console</text>
	</string>
	<string id="kb_contacts">
		<text>Contacts in the PDA</text>
	</string>
	<string id="kb_crouch">
		<text>Crouch</text>
	</string>
	<string id="kb_crouch_toggle">
		<text>Crouch toggle</text>
	</string>
	<string id="kb_detector">
		<text>Detector</text>
	</string>
	<string id="kb_down">
		<text>Down</text>
	</string>
	<string id="kb_drop">
		<text>Drop</text>
	</string>
	<string id="kb_fire">
		<text>Fire</text>
	</string>
	<string id="kb_firemode_next">
		<text>Next firing mode</text>
	</string>
	<string id="kb_firemode_prev">
		<text>Previous firing mode</text>
	</string>
	<string id="kb_forward">
		<text>Forward</text>
	</string>
	<string id="kb_func">
		<text>Under-barrel GL|Left hand Zoom</text>
	</string>
	<string id="kb_grp_common">
		<text>General</text>
	</string>
	<string id="kb_grp_direction">
		<text>Direction</text>
	</string>
	<string id="kb_grp_inventory">
		<text>Inventory</text>
	</string>
	<string id="kb_grp_movement">
		<text>Movement</text>
	</string>
	<string id="kb_grp_actions">
		<text>Actions</text>
	</string>
	<string id="kb_grp_multiplayer">
		<text>Multiplayer</text>
	</string>
	<string id="kb_grp_vehicles">
		<text>Vehicles</text>
	</string>
	<string id="kb_grp_companions">
		<text>Companions</text>
	</string>
	<string id="kb_grp_weapons">
		<text>Weapons</text>
	</string>
	<string id="kb_inventory">
		<text>Inventory</text>
	</string>
	<string id="kb_jump">
		<text>Jump</text>
	</string>
	<string id="kb_left">
		<text>Left</text>
	</string>
	<string id="kb_left_lookout">
		<text>Lean left</text>
	</string>
	<string id="kb_left_strafe">
		<text>Strafe left</text>
	</string>
	<string id="kb_map">
		<text>Map</text>
	</string>
	<string id="kb_next_slot">
		<text>Next weapon</text>
	</string>
	<string id="kb_night_vision">
		<text>Night vision/Switch hologram</text>
	</string>
	<string id="kb_pause">
		<text>Pause</text>
	</string>
	<string id="kb_pda">
		<text>PDA</text>
	</string>
	<string id="kb_prev_slot">
		<text>Previous weapon</text>
	</string>
	<string id="kb_quit">
		<text>Exit</text>
	</string>
	<string id="kb_reload">
		<text>Reload</text>
	</string>
	<string id="kb_repair">
		<text>Repair</text>
	</string>
	<string id="kb_right">
		<text>Right</text>
	</string>
	<string id="kb_right_lookout">
		<text>Lean right</text>
	</string>
	<string id="kb_right_strafe">
		<text>Strafe right</text>
	</string>
	<string id="kb_scores">
		<text>Active task</text>
	</string>
	<string id="kb_screenshot">
		<text>Screenshot</text>
	</string>
	<string id="kb_skin_menu">
		<text>Model selection menu</text>
	</string>
	<string id="kb_sprint">
		<text>Sprint, Hold breath</text>
	</string>
	<string id="kb_kick">
		<text>Kick</text>
	</string>
	<string id="kb_head_rotation">
		<text>Turn head</text>
	</string>
	<string id="kb_team_menu">
		<text>Team selection menu</text>
	</string>
	<string id="kb_torch">
		<text>Flashlight</text>
	</string>
	<string id="kb_torch_mode">
		<text>Flashlight Mode</text>
	</string>
	<string id="kb_turn_engine">
		<text>Turn engine</text>
	</string>
	<string id="kb_switch_horn">
		<text>Horn</text>
	</string>
	<string id="kb_up">
		<text>Up</text>
	</string>
	<string id="kb_use">
		<text>Use</text>
	</string>
	<string id="kb_use_bandage">
		<text>Quick bandage</text>
	</string>
	<string id="kb_use_medkit">
		<text>Quick medkit</text>
	</string>
	<string id="kb_vote_begin">
		<text>Start vote</text>
	</string>
	<string id="kb_vote_menu">
		<text>Vote menu</text>
	</string>
	<string id="kb_vote_no">
		<text>Vote "No"</text>
	</string>
	<string id="kb_vote_yes">
		<text>Vote "Yes"</text>
	</string>
	<string id="kb_weapon1">
		<text>Holster 1\Scabbard</text>
	</string>
	<string id="kb_weapon2">
		<text>Left arm weapon</text>
	</string>
	<string id="kb_weapon3">
		<text>Right arm weapon</text>
	</string>
	<string id="kb_weapon4">
		<text>Grenades</text>
	</string>
	<string id="kb_weapon5">
		<text>Holster 2\Binoculars</text>
	</string>
	<string id="kb_weapon6">
		<text>Thrown items</text>
	</string>
	<string id="kb_wpn_next">
		<text>Next type of ammo</text>
	</string>
	<string id="kb_zoom">
		<text>Zoom</text>
	</string>
	<string id="speech_menu_group">
		<text>Voice messages (1)</text>
	</string>
	<string id="speech_menu_personal">
		<text>Voice messages (2)</text>
	</string>
	<string id="kb_quick_use_1">
		<text>Quick access slot (1)</text>
	</string>
	<string id="kb_quick_use_2">
		<text>Quick access slot (2)</text>
	</string>
	<string id="kb_quick_use_3">
		<text>Quick access slot (3)</text>
	</string>
	<string id="kb_quick_use_4">
		<text>Quick access slot (4)</text>
	</string>
	<string id="kb_cam_1">
		<text>1st person view</text>
	</string>
	<string id="kb_cam_2">
		<text>3rd person view (1)</text>
	</string>
	<string id="kb_cam_3">
		<text>3rd person view (2)</text>
	</string>
	<string id="kb_cam_autoaim">
		<text>3rd person auto-aim</text>
	</string>
	<string id="kb_cam_zoom_in">
		<text>Camera|Detector zoom in</text>
	</string>
	<string id="kb_cam_zoom_out">
		<text>Camera|Detector zoom out</text>
	</string>
	<string id="kb_custom1">
		<text>Squad: toggle combat</text>
	</string>
	<string id="kb_custom2">
		<text>Squad: toggle movement</text>
	</string>
	<string id="kb_custom3">
		<text>Squad: move-to-point</text>
	</string>
	<string id="kb_custom4">
		<text>Squad: toggle cover</text>
	</string>
	<string id="kb_custom5">
		<text>Squad: toggle looting</text>
	</string>
	<string id="kb_hud_draw">
		<text>Toggle HUD</text>
	</string>
	<string id="kb_quick_release">
		<text>Quick release backpack</text>
	</string>
	<string id="kb_companion_menu">
		<text>Companion menu</text>
	</string>
	<string id="kb_take_off_mask">
		<text>Take off\put on helmet</text>
	</string>
	<string id="kb_switch_aim">
		<text>Aim switch</text>
	</string>
	<string id="kb_check_pulse">
		<text>Check pulse</text>
	</string>
	<string id="kb_mag_check">
		<text>Magazine check</text>
	</string>
	<string id="kb_mask_wipe">
		<text>Wipe mask</text>
	</string>
	<string id="kb_knife_attack">
		<text>Quick knife attack</text>
	</string>
	<string id="kb_toggle_minimap">
		<text>Toggle minimap</text>
	</string>
	<string id="kb_pda_tab1">
		<text>PDA Map</text>
	</string>
	<string id="kb_pda_tab2">
		<text>PDA Relations</text>
	</string>
	<string id="kb_pda_tab3">
		<text>PDA Contacts</text>
	</string>
	<string id="kb_pda_tab4">
		<text>PDA Statistics</text>
	</string>
	<string id="kb_pda_tab5">
		<text>PDA Messages</text>
	</string>
	<string id="kb_pda_tab6">
		<text>PDA Diary</text>
	</string>
	<string id="kb_pda_tab7">
		<text>PDA Skills</text>
	</string>
	<string id="kb_game_options">
		<text>Options window</text>
	</string>
</string_table>